<GeoServerTileLayer>
  <id>LayerInfoImpl--6fb7a615:180261407e3:-7ffe</id>
  <enabled>true</enabled>
  <inMemoryCached>true</inMemoryCached>
  <name>WADNRForestHealth:vGeoServerPclVectorRanked</name>
  <mimeFormats>
    <string>image/png</string>
    <string>image/jpeg</string>
  </mimeFormats>
  <gridSubsets>
    <gridSubset>
      <gridSetName>EPSG:4326</gridSetName>
      <extent>
        <coords>
          <double>-120.67365846289334</double>
          <double>47.76151587771068</double>
          <double>-120.53229524153915</double>
          <double>47.93337576309534</double>
        </coords>
      </extent>
    </gridSubset>
    <gridSubset>
      <gridSetName>EPSG:900913</gridSetName>
      <extent>
        <coords>
          <double>-1.3433330212250693E7</double>
          <double>6067270.88312314</double>
          <double>-1.341759373043265E7</double>
          <double>6095778.0841951175</double>
        </coords>
      </extent>
    </gridSubset>
  </gridSubsets>
  <metaWidthHeight>
    <int>4</int>
    <int>4</int>
  </metaWidthHeight>
  <expireCache>0</expireCache>
  <expireClients>0</expireClients>
  <parameterFilters>
    <styleParameterFilter>
      <key>STYLES</key>
      <defaultValue></defaultValue>
      <availableStyles class="sorted-set"/>
      <defaultStyle>WADNRForestHealth:PCL_bolder_color</defaultStyle>
    </styleParameterFilter>
  </parameterFilters>
  <gutter>0</gutter>
</GeoServerTileLayer>